Workbook
Name profit_margin2nds: '1. Расчет проекта'!$I$57
Name Принятое_решение_по_риску: '2. Расчет трудозатрат'!$F$66:$F$74
Name Project_name: '1. Расчет проекта'!$B$7
Name participants: '1. Расчет проекта'!$B$4
Name profit_margin1nds: '1. Расчет проекта'!$I$56
Name Увеличение_прямых_расходов: #REF!
Name margin: '1. Расчет проекта'!$K$46
Name cost2: '1. Расчет проекта'!$I$40
Name cost_1: '1. Расчет проекта'!$K$26
Name date: '1. Расчет проекта'!$B$2
Name cost_3: '1. Расчет проекта'!$I$45
Name BaseRisk: '1. Расчет проекта'!$D$18
Name price_1: '1. Расчет проекта'!$I$50
Name PM: '1. Расчет проекта'!$D$16
Name Решение_по_риску: '2. Расчет трудозатрат'!$F$66:$F$74
Name duration_day: '1. Расчет проекта'!$E$15
Name duration_month: '1. Расчет проекта'!$D$15
Name PMHours: '1. Расчет проекта'!$J$24
Name cost1: '1. Расчет проекта'!$K$26
Name profit_margin2: '1. Расчет проекта'!$I$49
Name Увеличение_трудозатрат: '2. Расчет трудозатрат'!$D$66:$D$74
Name FG: #REF!
Name cost_3nds: '1. Расчет проекта'!$I$53
Name ФГ: #REF!
Name Исполнитель: '2. Расчет трудозатрат'!$E$66:$E$74
Name cost_2nds: '1. Расчет проекта'!$I$41
Name PM_Org: #REF!
Name T_Risks: '2. Расчет трудозатрат'!$A$66:$F$74
Name PA_name: '1. Расчет проекта'!$B$3
Name profit_margin1: '1. Расчет проекта'!$I$48
Name cost_1nds: '1. Расчет проекта'!$K$30
Name Сustomer: '1. Расчет проекта'!$B$6
Name URL: '1. Расчет проекта'!$B$8
Name price_1nds: '1. Расчет проекта'!$I$58
Name T_Rates_ГИП: '1. Расчет проекта'!$K$28

Sheet 1. Расчет проекта
A1: Данные по проекту | G1: Стоимость по исполнителям
A2: Дата | B2: ГГГГ.ММ.ДД | G2: Роль | I2: Стоимость 1 часа без НДС | J2: Кол-во часов | K2: Стоимость | L2: Стоимость с учётом 5.Cкоринг | M2: Контрольные значения | N2: Контрольные значения
A3: Примечание (для учёта в оценке) | B3: лид / лид / Ещё чей-то лид / Своя продажа | G3: Исполнители | M3: по исполнителям
A4: Кто готовил калькулятор | B4: PM | G4: ='7. Ставки'!B3 -> #REF! | H4: ='7. Ставки'!C3 -> #REF! | I4: =IFERROR(VLOOKUP(H4, '7. Ставки'!$C$3:$E$19, 2, FALSE),"") | J4: =#REF! -> #REF! | K4: =I4*J4 -> #REF! | L4: =K4+(K4*$D$18) -> #REF! | M4: =SUM(K4:K20) -> #REF! | N4: чистая
B5: Architect | G5: ='7. Ставки'!B4 -> #REF! | H5: ='7. Ставки'!C4 -> #REF! | I5: =IFERROR(VLOOKUP(H5, '7. Ставки'!$C$3:$E$19, 2, FALSE),"") | J5: =#REF! -> #REF! | K5: =I5*J5 -> #REF! | L5: =K5+(K5*$D$18) -> #REF! | M5: =SUM(L4:L20) -> #REF! | N5: Со скорингом
A6: Заказчик | B6: Очень богатая компания | G6: ='7. Ставки'!B5 -> #REF! | H6: ='7. Ставки'!C5 -> #REF! | I6: =IFERROR(VLOOKUP(H6, '7. Ставки'!$C$3:$E$19, 2, FALSE),"") | J6: =#REF! -> #REF! | K6: =I6*J6 -> #REF! | L6: =K6+(K6*$D$18) -> #REF!
A7: Наименование проекта | B7: Очень большой РАГ | G7: ='7. Ставки'!B6 -> #REF! | H7: ='7. Ставки'!C6 -> #REF! | I7: =IFERROR(VLOOKUP(H7, '7. Ставки'!$C$3:$E$19, 2, FALSE),"") | J7: =#REF! -> #REF! | K7: =I7*J7 -> #REF! | L7: =K7+(K7*$D$18) -> #REF!
A8: Ссылка на сделку/заявку в CRM | B8: amo-crm | G8: ='7. Ставки'!B7 -> #REF! | H8: ='7. Ставки'!C7 -> #REF! | I8: =IFERROR(VLOOKUP(H8, '7. Ставки'!$C$3:$E$19, 2, FALSE),"") | J8: =#REF! -> #REF! | K8: =I8*J8 -> #REF! | L8: =K8+(K8*$D$18) -> #REF!
A9: Срок действия расчета, мес | B9: 6 | G9: ='7. Ставки'!B8 -> #REF! | H9: ='7. Ставки'!C8 -> #REF! | I9: =IFERROR(VLOOKUP(H9, '7. Ставки'!$C$3:$E$19, 2, FALSE),"") | J9: =#REF! -> #REF! | K9: =I9*J9 -> #REF! | L9: =K9+(K9*$D$18) -> #REF!
A10: По истечении срока действия расчет должен быть актуализирован. | G10: ='7. Ставки'!B9 -> #REF! | H10: ='7. Ставки'!C9 -> #REF! | I10: =IFERROR(VLOOKUP(H10, '7. Ставки'!$C$3:$E$19, 2, FALSE),"") | J10: =#REF! -> #REF! | K10: =I10*J10 -> #REF! | L10: =K10+(K10*$D$18) -> #REF!
G11: ='7. Ставки'!B10 -> #REF! | H11: ='7. Ставки'!C10 -> #REF! | I11: =IFERROR(VLOOKUP(H11, '7. Ставки'!$C$3:$E$19, 2, FALSE),"") | J11: =#REF! -> #REF! | K11: =I11*J11 -> #REF! | L11: =K11+(K11*$D$18) -> #REF!
G12: ='7. Ставки'!B11 -> #REF! | H12: ='7. Ставки'!C11 -> #REF! | I12: =IFERROR(VLOOKUP(H12, '7. Ставки'!$C$3:$E$19, 2, FALSE),"") | J12: =#REF! -> #REF! | K12: =I12*J12 -> #REF! | L12: =K12+(K12*$D$18) -> #REF!
A13: Управление | G13: ='7. Ставки'!B12 -> #REF! | H13: ='7. Ставки'!C12 -> #REF! | I13: =IFERROR(VLOOKUP(H13, '7. Ставки'!$C$3:$E$19, 2, FALSE),"") | J13: =#REF! -> #REF! | K13: =I13*J13 -> #REF! | L13: =K13+(K13*$D$18) -> #REF!
A14: Длительность проекта (8.КП) | B14: В часах без потерь | C14: В часах | D14: В месяцах | E14: В раб.днях | G14: ='7. Ставки'!B13 -> #REF! | H14: ='7. Ставки'!C13 -> #REF! | I14: =IFERROR(VLOOKUP(H14, '7. Ставки'!$C$3:$E$19, 2, FALSE),"") | J14: =#REF! -> #REF! | K14: =I14*J14 -> #REF! | L14: =K14+(K14*$D$18) -> #REF!
A15: (! не равна трудоёмкости) | C15: ='8. КП'!CP107 -> #REF! | D15: =ROUND(E15/21,1) -> #REF! | E15: ='8. КП'!DO107 -> #REF! | G15: ='7. Ставки'!B14 -> #REF! | H15: ='7. Ставки'!C14 -> #REF! | I15: =IFERROR(VLOOKUP(H15, '7. Ставки'!$C$3:$E$19, 2, FALSE),"") | J15: =#REF! -> #REF! | K15: =I15*J15 -> #REF! | L15: =K15+(K15*$D$18) -> #REF!
A16: Управление проектом (3. Уровень обслуживания) | D16: РП (Обычный проект) | G16: ='7. Ставки'!B15 -> #REF! | H16: ='7. Ставки'!C15 -> #REF! | I16: =IFERROR(VLOOKUP(H16, '7. Ставки'!$C$3:$E$19, 2, FALSE),"") | J16: =#REF! -> #REF! | K16: =I16*J16 -> #REF! | L16: =K16+(K16*$D$18) -> #REF!
A17: Управление разработкой Команда проекта (3. Уровень обслуживания) | D17: Team3 (Обычный проект от 2Dev+1DS или 2DS+1Dev) | G17: ='7. Ставки'!B16 -> #REF! | H17: ='7. Ставки'!C16 -> #REF! | I17: =IFERROR(VLOOKUP(H17, '7. Ставки'!$C$3:$E$19, 2, FALSE),"") | J17: =#REF! -> #REF! | K17: =I17*J17 -> #REF! | L17: =K17+(K17*$D$18) -> #REF!
A18: Уровень базового риска (5. Скоринг) | D18: ='3. Скоринг'!F15 -> 0.15 | G18: ='7. Ставки'!B17 -> #REF! | H18: ='7. Ставки'!C17 -> #REF! | I18: =IFERROR(VLOOKUP(H18, '7. Ставки'!$C$3:$E$19, 2, FALSE),"") | J18: =#REF! -> #REF! | K18: =I18*J18 -> #REF! | L18: =K18+(K18*$D$18) -> #REF!
G19: ='7. Ставки'!B18 -> #REF! | H19: ='7. Ставки'!C18 -> #REF! | I19: =IFERROR(VLOOKUP(H19, '7. Ставки'!$C$3:$E$19, 2, FALSE),"") | J19: =#REF! -> #REF! | K19: =I19*J19 -> #REF! | L19: =K19+(K19*$D$18) -> #REF!
A20: * базовые часы РП (3. Уровень обслуживания), для справки | D20: =VLOOKUP(G22,'3. Уровень обслуживания'!A3:D7,4,FALSE) -> #REF! | G20: ='7. Ставки'!B19 -> #REF! | H20: ='7. Ставки'!C19 -> #REF! | I20: =IFERROR(VLOOKUP(H20, '7. Ставки'!$C$3:$E$19, 2, FALSE),"") | J20: =#REF! -> #REF! | K20: =I20*J20 -> #REF! | L20: =K20+(K20*$D$18) -> #REF!
G21: Руководство проектом | I21: =IFERROR(VLOOKUP(H21, '7. Ставки'!$C$3:$E$19, 2, FALSE),"") | M21: прирост стоимости по управлению | N21: =CONCATENATE("+ ",ROUND(((M23/M5))*100,1),"%") -> #REF!
G22: =D16 -> РП (Обычный проект) | H22: ='7. Ставки'!C11 -> #REF! | I22: =IFERROR(VLOOKUP(H22, '7. Ставки'!$C$3:$E$19, 2, FALSE),"") | J22: =VLOOKUP(G22,'3. Уровень обслуживания'!A4:B7, 2,FALSE) -> #REF! | K22: =I22*J22 -> #REF! | L22: =K22+(K22*$D$18) -> #REF! | M22: =SUM(K22:K25) -> #REF! | N22: чистая
G23: Архитектурный надзор | H23: ='7. Ставки'!C16 -> #REF! | I23: =IFERROR(VLOOKUP(H23, '7. Ставки'!$C$3:$E$19, 2, FALSE),"") | J23: =#REF! -> #REF! | K23: =I23*J23 -> #REF! | L23: =K23+(K23*$D$18) -> #REF! | M23: =SUM(L22:L25) -> #REF! | N23: Со скорингом
G24: Тимлидерство | H24: ='7. Ставки'!C3 -> #REF! | I24: =IFERROR(VLOOKUP(H24, '7. Ставки'!$C$3:$E$19, 2, FALSE),"") | J24: =#REF! -> #REF! | K24: =I24*J24 -> #REF! | L24: =K24+(K24*$D$18) -> #REF!
G25: ИИ Лидерство | H25: ='7. Ставки'!C4 -> #REF! | I25: =IFERROR(VLOOKUP(H25, '7. Ставки'!$C$3:$E$19, 2, FALSE),"") | J25: =#REF! -> #REF! | K25: =I25*J25 -> #REF! | L25: =K25+(K25*$D$18) -> #REF!
G26: Итого стоимость (с учётом данных из таблицы ниже "Прямые расходы") без НДС | K26: =SUM(K3:K25)+cost2 -> #REF! | L26: =SUM(L3:L25)+cost2 -> #REF! | M26: доля включённых в стоимость рисков и прямых затрат ОТ конечной суммы (уже с учётом скоринга) | N26: =CONCATENATE("",ROUND((SUM(L27:L29)/L26)*100,1),"% включено") -> #REF!
I27: Добавляет 5.Скоринг | K27: n/a | L27: =L26-K26 -> #REF! | M27: =CONCATENATE("",ROUND(((L27/L26))*100,1),"%") -> #REF! | N27: * процент от конечной стоимсоти (считается делением в обратную сторону, относительно наложения скоринга, поэтому меньше его)
A28: Внимание: Заполнять в шаблоне требуется поля с желтой заливкой. | I28: Добавляет 2.Расчёт трудозатрат (Идентифицированные риски:) | K28: =#REF! -> #REF! | L28: =#REF! -> #REF! | M28: =CONCATENATE("",ROUND(((L28/L26))*100,1),"%") -> #REF! | N28: включено
A29: Поля с серой заливкой - справочные, либо рассчитываются автоматически по формулам | G29: В том числе прямые расходы: | I29: Добавляет 1.Расчёт проекта (Прямые расходы без НДС) | K29: =cost2 -> #REF! | L29: =cost2 -> #REF! | M29: =CONCATENATE("",ROUND(((L29/L26))*100,1),"%") -> #REF! | N29: включено
G30: Итого стоимость с НДС (справочно) | J30: 0.05 | K30: =SUM(K3:K24)+(SUM(K3:K24)*$J$30)+cost_2nds -> #REF! | L30: =SUM(L3:L24)+(SUM(L3:L24)*$J$30)+cost_2nds -> #REF!
L33: 1.07
G34: Прямые расходы | L34: =8216693*L33 -> 8791861.5
G35: Наименование | I35: Сумма
G36: Командировочные расходы | I36: ='4. Командировочные'!B25 -> #REF!
G37: Прочие прямые расходы | I37: 0
G38: Себестоимость лицензий | I38: 0
G39: Себестоимость хостинга (в год) | I39: 0
G40: Итого прямые расходы без НДС | I40: =IF(A12="Бюджетирование предусматривает дополнительный рост себестоимости на 10%",SUM(I36:I39)*1.1,SUM(I36:I39)) -> #REF! | J40: cost2
G41: Итого прямые расходы c НДС | I41: =cost2*1.05 -> #REF! | J41: cost2nds
G44: C. Расчет стоимости без НДС
G45: Всего расходов | I45: =cost1+cost2 -> #REF! | K45: Маржа:
G46: Коэффициент маржинальности | I46: =1/((1-K46)*(1-0.005)) -> 1.1823825 | K46: 0.15
G47: Отчисления в риск фонд | I47: =price_1*0.005 -> #REF!
G48: Грязная маржа проекта | I48: =price_1-cost2-I47 -> #REF!
G49: Чистая маржа проекта | I49: =price_1-cost_3-I47 -> #REF!
G50: Итого стоимость для заказчика без НДС | I50: =cost_3*I46 -> #REF!
G52: D. Расчет стоимости с НДС
G53: Всего расходов | I53: =cost_1nds+cost_2nds -> #REF!
G54: Коэффициент маржинальности | I54: =1/((1-K46)*(1-0.005)) -> 1.1823825
G55: Отчисления в риск фонд | I55: =price_1nds*0.005 -> #REF!
G56: Грязная маржа проекта | I56: =price_1nds-cost_2nds-I55 -> #REF!
G57: Чистая маржа проекта | I57: =price_1nds-cost_3nds-I55 -> #REF!
G58: Итого стоимость для заказчика с НДС | I58: =cost_3nds*I54 -> #REF!

Sheet 2. Расчет трудозатрат
A1: Калькулятор расчета трудозатрат | P1: Размерность | Q1: 1000 | R1: Риск
C2: 1 | D2: =C2+1 -> 2 | E2: =D2+1 -> 3 | F2: =E2+1 -> 4 | G2: =F2+1 -> 5 | H2: =G2+1 -> 6 | I2: =H2+1 -> 7 | J2: =I2+1 -> 8 | K2: =J2+1 -> 9 | L2: =K2+1 -> 10 | P2: Округления | Q2: 2 | R2: ='1. Расчет проекта'!D18 -> 0.15 | T2: =L2+8 -> 18
A3: № | B3: Группа Grooup | C3: Наименование работ (as option Task for ETS) | D3: Чел./час (ч.) базовые | E3: Исполнитель | F3: Доля занятости | G3: Параллельные потоки | H3: Этапы по КП | I3: Список ограничений и требований к Заказчику | J3: Ожидаемые результаты | K3: Длительность этапа (раб дни послед-но) | L3: Командировка (да/нет) | N3: Риск на длительность | P3: Стоимость роли | Q3: Стоимость задачи | R3: Стоимость с учётом 5.Скоринг | T3: ETS Line | U3: ETS Role | V3: ETS Hours
A4: 0 | B4: Managment (Управление) | C4: =CONCATENATE('1. Расчет проекта'!G22,"; ","Договорная работа, оплата, отчёты") -> РП (Обычный проект); Договорная работа, оплата, отчёты | D4: ='1. Расчет проекта'!J22*I4 -> #REF! | E4: ='1. Расчет проекта'!H22 -> #REF! | F4: =ROUND(D4/(K4*8),2) -> #REF! | I4: 0.2 | J4: доля часов из общего объёма на активность | K4: ='1. Расчет проекта'!$E$15 -> #REF! | L4: Нет | N4: 1 | P4: =IFERROR(IF(E4="","",VLOOKUP(E4,'7. Ставки'!$C$3:$E$19,2,0)),"УКАЖИ РОЛЬ") -> УКАЖИ РОЛЬ | Q4: =IFERROR(IF(OR(D4=0,P4=0,D4="",P4=""),"",D4*P4),"ПРОВЕРЬ ЦИФРЫ") -> ПРОВЕРЬ ЦИФРЫ | R4: =IF(Q4="","",Q4+(Q4*$R$2)) -> #VALUE! | S4: без НДС | T4: =IF(OR(D4="",D4=0),"",CONCATENATE(E4," ",C4)) -> #REF! | U4: =IF(OR(D4="",D4=0),"",E4) -> #REF! | V4: =IF(OR(D4="",D4=0),"",D4) -> #REF!
B5: ГРУППУ НЕ МЕНЯТЬ | C5: =CONCATENATE('1. Расчет проекта'!G22,"; ","Коммуникация daily, weekly, calls etc.") -> РП (Обычный проект); Коммуникация daily, weekly, calls etc. | D5: ='1. Расчет проекта'!J22*I5 -> #REF! | E5: ='1. Расчет проекта'!H22 -> #REF! | F5: =ROUND(D5/(K5*8),2) -> #REF! | I5: 0.7 | J5: доля часов из общего объёма на активность | K5: ='1. Расчет проекта'!$E$15 -> #REF! | L5: Нет | P5: =IFERROR(IF(E5="","",VLOOKUP(E5,'7. Ставки'!$C$3:$E$19,2,0)),"УКАЖИ РОЛЬ") -> УКАЖИ РОЛЬ | Q5: =IFERROR(IF(OR(D5=0,P5=0,D5="",P5=""),"",D5*P5),"ПРОВЕРЬ ЦИФРЫ") -> ПРОВЕРЬ ЦИФРЫ | R5: =IF(Q5="","",Q5+(Q5*$R$2)) -> #VALUE! | S5: без НДС | T5: =IF(OR(D5="",D5=0),"",CONCATENATE(E5," ",C5)) -> #REF! | U5: =IF(OR(D5="",D5=0),"",E5) -> #REF! | V5: =IF(OR(D5="",D5=0),"",D5) -> #REF!
B6: РАСЧЁТ АВТОМАТИЧЕСКИЙ | C6: =CONCATENATE('1. Расчет проекта'!G22,"; ","Постановка задач, управление командой") -> РП (Обычный проект); Постановка задач, управление командой | D6: ='1. Расчет проекта'!J22*I6 -> #REF! | E6: ='1. Расчет проекта'!H22 -> #REF! | F6: =ROUND(D6/(K6*8),2) -> #REF! | I6: =1-SUM(I4:I5) -> 0.1 | J6: доля часов из общего объёма на активность | K6: ='1. Расчет проекта'!$E$15 -> #REF! | L6: Нет | N6: НЕ ТРОГАТЬ | P6: =IFERROR(IF(E6="","",VLOOKUP(E6,'7. Ставки'!$C$3:$E$19,2,0)),"УКАЖИ РОЛЬ") -> УКАЖИ РОЛЬ | Q6: =IFERROR(IF(OR(D6=0,P6=0,D6="",P6=""),"",D6*P6),"ПРОВЕРЬ ЦИФРЫ") -> ПРОВЕРЬ ЦИФРЫ | R6: =IF(Q6="","",Q6+(Q6*$R$2)) -> #VALUE! | S6: без НДС | T6: =IF(OR(D6="",D6=0),"",CONCATENATE(E6," ",C6)) -> #REF! | U6: =IF(OR(D6="",D6=0),"",E6) -> #REF! | V6: =IF(OR(D6="",D6=0),"",D6) -> #REF!
B7: ВСЕ ДАННЫЕ | C7: ='1. Расчет проекта'!G23 -> Архитектурный надзор | D7: ='1. Расчет проекта'!J23 -> #REF! | E7: ='1. Расчет проекта'!H23 -> #REF! | F7: =ROUND(D7/(K7*8),2) -> #REF! | K7: ='1. Расчет проекта'!$E$15 -> #REF! | L7: Нет | N7: СЕРЫЕ | P7: =IFERROR(IF(E7="","",VLOOKUP(E7,'7. Ставки'!$C$3:$E$19,2,0)),"УКАЖИ РОЛЬ") -> УКАЖИ РОЛЬ | Q7: =IFERROR(IF(OR(D7=0,P7=0,D7="",P7=""),"",D7*P7),"ПРОВЕРЬ ЦИФРЫ") -> ПРОВЕРЬ ЦИФРЫ | R7: =IF(Q7="","",Q7+(Q7*$R$2)) -> #VALUE! | S7: без НДС | T7: =IF(OR(D7="",D7=0),"",CONCATENATE(E7," ",C7)) -> #REF! | U7: =IF(OR(D7="",D7=0),"",E7) -> #REF! | V7: =IF(OR(D7="",D7=0),"",D7) -> #REF!
B8: ЗАИМСТВОВАНЫ с стр.1 | C8: =CONCATENATE('1. Расчет проекта'!G24,"; ","Код-ревью и разработка") -> Тимлидерство; Код-ревью и разработка | D8: ='1. Расчет проекта'!J24*I8 -> #REF! | E8: ='1. Расчет проекта'!H24 -> #REF! | F8: =ROUND(D8/(K8*8),2) -> #REF! | I8: 0.5 | J8: доля часов из общего объёма на активность | K8: ='1. Расчет проекта'!$E$15 -> #REF! | L8: Нет | N8: ЯЧЕЙКИ | P8: =IFERROR(IF(E8="","",VLOOKUP(E8,'7. Ставки'!$C$3:$E$19,2,0)),"УКАЖИ РОЛЬ") -> УКАЖИ РОЛЬ | Q8: =IFERROR(IF(OR(D8=0,P8=0,D8="",P8=""),"",D8*P8),"ПРОВЕРЬ ЦИФРЫ") -> ПРОВЕРЬ ЦИФРЫ | R8: =IF(Q8="","",Q8+(Q8*$R$2)) -> #VALUE! | S8: без НДС | T8: =IF(OR(D8="",D8=0),"",CONCATENATE(E8," ",C8)) -> #REF! | U8: =IF(OR(D8="",D8=0),"",E8) -> #REF! | V8: =IF(OR(D8="",D8=0),"",D8) -> #REF!
C9: =CONCATENATE('1. Расчет проекта'!G24,"; ","Декомпозиция задач, постановка задач, управление командой") -> Тимлидерство; Декомпозиция задач, постановка задач, управление командой | D9: ='1. Расчет проекта'!J24*I9 -> #REF! | E9: TL | F9: =ROUND(D9/(K9*8),2) -> #REF! | I9: =1-SUM(I8) -> 0.5 | J9: доля часов из общего объёма на активность | K9: ='1. Расчет проекта'!$E$15 -> #REF! | L9: Нет | P9: =IFERROR(IF(E9="","",VLOOKUP(E9,'7. Ставки'!$C$3:$E$19,2,0)),"УКАЖИ РОЛЬ") -> УКАЖИ РОЛЬ | Q9: =IFERROR(IF(OR(D9=0,P9=0,D9="",P9=""),"",D9*P9),"ПРОВЕРЬ ЦИФРЫ") -> ПРОВЕРЬ ЦИФРЫ | R9: =IF(Q9="","",Q9+(Q9*$R$2)) -> #VALUE! | T9: =IF(OR(D9="",D9=0),"",CONCATENATE(E9," ",C9)) -> #REF! | U9: =IF(OR(D9="",D9=0),"",E9) -> #REF! | V9: =IF(OR(D9="",D9=0),"",D9) -> #REF!
C10: =CONCATENATE('1. Расчет проекта'!G25,"; ","Код-ревью и разработка") -> ИИ Лидерство; Код-ревью и разработка | D10: ='1. Расчет проекта'!J25*I10 -> #REF! | E10: DSLead | F10: =ROUND(D10/(K10*8),2) -> #REF! | I10: 0.5 | J10: доля часов из общего объёма на активность | K10: ='1. Расчет проекта'!$E$15 -> #REF! | L10: Нет | P10: =IFERROR(IF(E10="","",VLOOKUP(E10,'7. Ставки'!$C$3:$E$19,2,0)),"УКАЖИ РОЛЬ") -> УКАЖИ РОЛЬ | Q10: =IFERROR(IF(OR(D10=0,P10=0,D10="",P10=""),"",D10*P10),"ПРОВЕРЬ ЦИФРЫ") -> ПРОВЕРЬ ЦИФРЫ | R10: =IF(Q10="","",Q10+(Q10*$R$2)) -> #VALUE! | T10: =IF(OR(D10="",D10=0),"",CONCATENATE(E10," ",C10)) -> #REF! | U10: =IF(OR(D10="",D10=0),"",E10) -> #REF! | V10: =IF(OR(D10="",D10=0),"",D10) -> #REF!
C11: =CONCATENATE('1. Расчет проекта'!G25,"; ","Декомпозиция задач, постановка задач, управление командой") -> ИИ Лидерство; Декомпозиция задач, постановка задач, управление командой | D11: ='1. Расчет проекта'!J25*I11 -> #REF! | E11: DSLead | F11: =ROUND(D11/(K11*8),2) -> #REF! | I11: =1-SUM(I10) -> 0.5 | J11: доля часов из общего объёма на активность | K11: ='1. Расчет проекта'!$E$15 -> #REF! | L11: Нет | P11: =IFERROR(IF(E11="","",VLOOKUP(E11,'7. Ставки'!$C$3:$E$19,2,0)),"УКАЖИ РОЛЬ") -> УКАЖИ РОЛЬ | Q11: =IFERROR(IF(OR(D11=0,P11=0,D11="",P11=""),"",D11*P11),"ПРОВЕРЬ ЦИФРЫ") -> ПРОВЕРЬ ЦИФРЫ | R11: =IF(Q11="","",Q11+(Q11*$R$2)) -> #VALUE! | T11: =IF(OR(D11="",D11=0),"",CONCATENATE(E11," ",C11)) -> #REF! | U11: =IF(OR(D11="",D11=0),"",E11) -> #REF! | V11: =IF(OR(D11="",D11=0),"",D11) -> #REF!
K12: =IFERROR(IF(OR(F12=0,D12=0,F12="",D12=""),"",ROUNDUP('2. Расчет трудозатрат'!$D12/8*$N$4/'2. Расчет трудозатрат'!$F12,0)),"ПРОВЕРЬ ЦИФРЫ") | L12: Нет | P12: =IFERROR(IF(E12="","",VLOOKUP(E12,'7. Ставки'!$C$3:$E$19,2,0)),"УКАЖИ РОЛЬ") | Q12: =IFERROR(IF(OR(D12=0,P12=0,D12="",P12=""),"",D12*P12),"ПРОВЕРЬ ЦИФРЫ") | R12: =IF(Q12="","",Q12+(Q12*$R$2)) | S12: без НДС | T12: =IF(OR(D12="",D12=0),"",CONCATENATE(E12," ",C12)) | U12: =IF(OR(D12="",D12=0),"",E12) | V12: =IF(OR(D12="",D12=0),"",D12)
Q13: =SUM(Q4:Q12) -> 0 | R13: =SUM(R4:R12) -> #VALUE! | S13: без НДС | T13: =IF(OR(D13="",D13=0),"",CONCATENATE(E13," ",C13)) | U13: =IF(OR(D13="",D13=0),"",E13) | V13: =IF(OR(D13="",D13=0),"",D13)
A14: 1 | B14: RnD (Исследование) | K14: =IFERROR(IF(OR(F14=0,D14=0,F14="",D14=""),"",ROUNDUP('2. Расчет трудозатрат'!$D14/8*$N$4/'2. Расчет трудозатрат'!$F14,0)),"ПРОВЕРЬ ЦИФРЫ") | P14: =IFERROR(IF(E14="","",VLOOKUP(E14,'7. Ставки'!$C$3:$E$19,2,0)),"УКАЖИ РОЛЬ") | Q14: =IFERROR(IF(OR(D14=0,P14=0,D14="",P14=""),"",D14*P14),"ПРОВЕРЬ ЦИФРЫ") | R14: =IF(Q14="","",Q14+(Q14*$R$2)) | S14: без НДС | T14: =IF(OR(D14="",D14=0),"",CONCATENATE(E14," ",C14)) | U14: =IF(OR(D14="",D14=0),"",E14) | V14: =IF(OR(D14="",D14=0),"",D14)
A15: 2 | B15: Design (Пре.проект) | P15: =IFERROR(IF(E15="","",VLOOKUP(E15,'7. Ставки'!$C$3:$E$19,2,0)),"УКАЖИ РОЛЬ") | Q15: =IFERROR(IF(OR(D15=0,P15=0,D15="",P15=""),"",D15*P15),"ПРОВЕРЬ ЦИФРЫ") | R15: =IF(Q15="","",Q15+(Q15*$R$2)) | T15: =IF(OR(D15="",D15=0),"",CONCATENATE(E15," ",C15)) | U15: =IF(OR(D15="",D15=0),"",E15) | V15: =IF(OR(D15="",D15=0),"",D15)
C16: Уточнение требований, интервью со стейкхолдерами | D16: 24 | E16: Analytics Busines | F16: 1 | G16: 1 | H16: 1 | I16: Предоставить контактных лиц, доступы к Confluence, ERP | J16: Финализированный и утвержденный документ с требованиями (PRD) | K16: =IFERROR(IF(OR(F16=0,D16=0,F16="",D16=""),"",ROUNDUP('2. Расчет трудозатрат'!$D16/8*$N$4/'2. Расчет трудозатрат'!$F16,0)),"ПРОВЕРЬ ЦИФРЫ") -> 3 | L16: Нет | P16: =IFERROR(IF(E16="","",VLOOKUP(E16,'7. Ставки'!$C$3:$E$19,2,0)),"УКАЖИ РОЛЬ") -> УКАЖИ РОЛЬ | Q16: =IFERROR(IF(OR(D16=0,P16=0,D16="",P16=""),"",D16*P16),"ПРОВЕРЬ ЦИФРЫ") -> ПРОВЕРЬ ЦИФРЫ | R16: =IF(Q16="","",Q16+(Q16*$R$2)) -> #VALUE! | S16: без НДС | T16: =IF(OR(D16="",D16=0),"",CONCATENATE(E16," ",C16)) -> Analytics Busines Уточнение требований, интервью со стейкхолдерами | U16: =IF(OR(D16="",D16=0),"",E16) -> Analytics Busines | V16: =IF(OR(D16="",D16=0),"",D16) -> 24
C17: Проектирование высокоуровневой архитектуры | D17: 4 | E17: Architect | F17: 1 | G17: 1 | H17: 1 | J17: Утвержденная схема архитектуры, технологический стек | K17: =IFERROR(IF(OR(F17=0,D17=0,F17="",D17=""),"",ROUNDUP('2. Расчет трудозатрат'!$D17/8*$N$4/'2. Расчет трудозатрат'!$F17,0)),"ПРОВЕРЬ ЦИФРЫ") -> 1 | L17: Нет | P17: =IFERROR(IF(E17="","",VLOOKUP(E17,'7. Ставки'!$C$3:$E$19,2,0)),"УКАЖИ РОЛЬ") -> УКАЖИ РОЛЬ | Q17: =IFERROR(IF(OR(D17=0,P17=0,D17="",P17=""),"",D17*P17),"ПРОВЕРЬ ЦИФРЫ") -> ПРОВЕРЬ ЦИФРЫ | R17: =IF(Q17="","",Q17+(Q17*$R$2)) -> #VALUE! | S17: без НДС | T17: =IF(OR(D17="",D17=0),"",CONCATENATE(E17," ",C17)) -> Architect Проектирование высокоуровневой архитектуры | U17: =IF(OR(D17="",D17=0),"",E17) -> Architect | V17: =IF(OR(D17="",D17=0),"",D17) -> 4
C18: Проектирование API-контрактов между сервисами | D18: 8 | E18: Development Back | F18: 1 | G18: 1 | H18: 1 | J18: OpenAPI (Swagger) спецификации для всех внутренних сервисов | K18: =IFERROR(IF(OR(F18=0,D18=0,F18="",D18=""),"",ROUNDUP('2. Расчет трудозатрат'!$D18/8*$N$4/'2. Расчет трудозатрат'!$F18,0)),"ПРОВЕРЬ ЦИФРЫ") -> 1 | L18: Нет | P18: =IFERROR(IF(E18="","",VLOOKUP(E18,'7. Ставки'!$C$3:$E$19,2,0)),"УКАЖИ РОЛЬ") -> УКАЖИ РОЛЬ | Q18: =IFERROR(IF(OR(D18=0,P18=0,D18="",P18=""),"",D18*P18),"ПРОВЕРЬ ЦИФРЫ") -> ПРОВЕРЬ ЦИФРЫ | R18: =IF(Q18="","",Q18+(Q18*$R$2)) -> #VALUE! | S18: без НДС | T18: =IF(OR(D18="",D18=0),"",CONCATENATE(E18," ",C18)) -> Development Back Проектирование API-контрактов между сервисами | U18: =IF(OR(D18="",D18=0),"",E18) -> Development Back | V18: =IF(OR(D18="",D18=0),"",D18) -> 8
C19: Проектирование схемы хранения логов и метрик SLA | D19: 4 | E19: DevOps | F19: 1 | G19: 1 | H19: 1 | J19: Структура индексов в Elasticsearch, определены ключевые метрики | K19: =IFERROR(IF(OR(F19=0,D19=0,F19="",D19=""),"",ROUNDUP('2. Расчет трудозатрат'!$D19/8*$N$4/'2. Расчет трудозатрат'!$F19,0)),"ПРОВЕРЬ ЦИФРЫ") -> 1 | L19: Нет | P19: =IFERROR(IF(E19="","",VLOOKUP(E19,'7. Ставки'!$C$3:$E$19,2,0)),"УКАЖИ РОЛЬ") -> УКАЖИ РОЛЬ | Q19: =IFERROR(IF(OR(D19=0,P19=0,D19="",P19=""),"",D19*P19),"ПРОВЕРЬ ЦИФРЫ") -> ПРОВЕРЬ ЦИФРЫ | R19: =IF(Q19="","",Q19+(Q19*$R$2)) -> #VALUE! | S19: без НДС | T19: =IF(OR(D19="",D19=0),"",CONCATENATE(E19," ",C19)) -> DevOps Проектирование схемы хранения логов и метрик SLA | U19: =IF(OR(D19="",D19=0),"",E19) -> DevOps | V19: =IF(OR(D19="",D19=0),"",D19) -> 4
C20: Проектирование пайплайна индексации Confluence | D20: 16 | E20: DS/Ai/ML | F20: 1 | G20: 1 | H20: 1 | I20: Доступ к API Confluence. Ограничение: до 1000 страниц, парсинг сложных таблиц и макросов не входит в MVP. | J20: Детальная схема процесса индексации | K20: =IFERROR(IF(OR(F20=0,D20=0,F20="",D20=""),"",ROUNDUP('2. Расчет трудозатрат'!$D20/8*$N$4/'2. Расчет трудозатрат'!$F20,0)),"ПРОВЕРЬ ЦИФРЫ") -> 2 | L20: Нет | P20: =IFERROR(IF(E20="","",VLOOKUP(E20,'7. Ставки'!$C$3:$E$19,2,0)),"УКАЖИ РОЛЬ") -> УКАЖИ РОЛЬ | Q20: =IFERROR(IF(OR(D20=0,P20=0,D20="",P20=""),"",D20*P20),"ПРОВЕРЬ ЦИФРЫ") -> ПРОВЕРЬ ЦИФРЫ | R20: =IF(Q20="","",Q20+(Q20*$R$2)) -> #VALUE! | S20: без НДС | T20: =IF(OR(D20="",D20=0),"",CONCATENATE(E20," ",C20)) -> DS/Ai/ML Проектирование пайплайна индексации Confluence | U20: =IF(OR(D20="",D20=0),"",E20) -> DS/Ai/ML | V20: =IF(OR(D20="",D20=0),"",D20) -> 16
A21: 3 | B21: Development (Разработка) | P21: =IFERROR(IF(E21="","",VLOOKUP(E21,'7. Ставки'!$C$3:$E$19,2,0)),"УКАЖИ РОЛЬ") | Q21: =IFERROR(IF(OR(D21=0,P21=0,D21="",P21=""),"",D21*P21),"ПРОВЕРЬ ЦИФРЫ") | R21: =IF(Q21="","",Q21+(Q21*$R$2)) | T21: =IF(OR(D21="",D21=0),"",CONCATENATE(E21," ",C21)) | U21: =IF(OR(D21="",D21=0),"",E21) | V21: =IF(OR(D21="",D21=0),"",D21)
C22: Настройка Docker Swarm и связки Foundation Models | D22: 16 | E22: DevOps | F22: 1 | G22: 6 | H22: 2 | I22: Предоставить доступы к облачному провайдеру | J22: Готовая к развертыванию, безопасная K8s-инфраструктура | K22: =IFERROR(IF(OR(F22=0,D22=0,F22="",D22=""),"",ROUNDUP('2. Расчет трудозатрат'!$D22/8*$N$4/'2. Расчет трудозатрат'!$F22,0)),"ПРОВЕРЬ ЦИФРЫ") -> 2 | L22: Нет | P22: =IFERROR(IF(E22="","",VLOOKUP(E22,'7. Ставки'!$C$3:$E$19,2,0)),"УКАЖИ РОЛЬ") -> УКАЖИ РОЛЬ | Q22: =IFERROR(IF(OR(D22=0,P22=0,D22="",P22=""),"",D22*P22),"ПРОВЕРЬ ЦИФРЫ") -> ПРОВЕРЬ ЦИФРЫ | R22: =IF(Q22="","",Q22+(Q22*$R$2)) -> #VALUE! | S22: без НДС | T22: =IF(OR(D22="",D22=0),"",CONCATENATE(E22," ",C22)) -> DevOps Настройка Docker Swarm и связки Foundation Models | U22: =IF(OR(D22="",D22=0),"",E22) -> DevOps | V22: =IF(OR(D22="",D22=0),"",D22) -> 16
C23: Настройка CI/CD пайплайнов (GitLab CI / GitHub Actions) | D23: 4 | E23: DevOps | F23: 1 | G23: 7 | H23: 2 | I23: Доступ к репозиториям кода | J23: Автоматическая сборка, тестирование и развертывание сервисов | K23: =IFERROR(IF(OR(F23=0,D23=0,F23="",D23=""),"",ROUNDUP('2. Расчет трудозатрат'!$D23/8*$N$4/'2. Расчет трудозатрат'!$F23,0)),"ПРОВЕРЬ ЦИФРЫ") -> 1 | L23: Нет | P23: =IFERROR(IF(E23="","",VLOOKUP(E23,'7. Ставки'!$C$3:$E$19,2,0)),"УКАЖИ РОЛЬ") -> УКАЖИ РОЛЬ | Q23: =IFERROR(IF(OR(D23=0,P23=0,D23="",P23=""),"",D23*P23),"ПРОВЕРЬ ЦИФРЫ") -> ПРОВЕРЬ ЦИФРЫ | R23: =IF(Q23="","",Q23+(Q23*$R$2)) -> #VALUE! | S23: без НДС | T23: =IF(OR(D23="",D23=0),"",CONCATENATE(E23," ",C23)) -> DevOps Настройка CI/CD пайплайнов (GitLab CI / GitHub Actions) | U23: =IF(OR(D23="",D23=0),"",E23) -> DevOps | V23: =IF(OR(D23="",D23=0),"",D23) -> 4
C24: Развертывание баз данных (PostgreSQL, Redis, Qdrant) | D24: 4 | E24: DevOps | F24: 1 | G24: 8 | H24: 2 | J24: Развернутые и сконфигурированные инстансы хранилищ данных | K24: =IFERROR(IF(OR(F24=0,D24=0,F24="",D24=""),"",ROUNDUP('2. Расчет трудозатрат'!$D24/8*$N$4/'2. Расчет трудозатрат'!$F24,0)),"ПРОВЕРЬ ЦИФРЫ") -> 1 | L24: Нет | P24: =IFERROR(IF(E24="","",VLOOKUP(E24,'7. Ставки'!$C$3:$E$19,2,0)),"УКАЖИ РОЛЬ") -> УКАЖИ РОЛЬ | Q24: =IFERROR(IF(OR(D24=0,P24=0,D24="",P24=""),"",D24*P24),"ПРОВЕРЬ ЦИФРЫ") -> ПРОВЕРЬ ЦИФРЫ | R24: =IF(Q24="","",Q24+(Q24*$R$2)) -> #VALUE! | S24: без НДС | T24: =IF(OR(D24="",D24=0),"",CONCATENATE(E24," ",C24)) -> DevOps Развертывание баз данных (PostgreSQL, Redis, Qdrant) | U24: =IF(OR(D24="",D24=0),"",E24) -> DevOps | V24: =IF(OR(D24="",D24=0),"",D24) -> 4
C25: Настройка системы логирования и мониторинга (Prometheus, Grafana) | D25: 4 | E25: DevOps | F25: 1 | G25: 9 | H25: 2 | J25: Централизованный сбор логов, дашборды в Kibana и Grafana | K25: =IFERROR(IF(OR(F25=0,D25=0,F25="",D25=""),"",ROUNDUP('2. Расчет трудозатрат'!$D25/8*$N$4/'2. Расчет трудозатрат'!$F25,0)),"ПРОВЕРЬ ЦИФРЫ") -> 1 | L25: Нет | P25: =IFERROR(IF(E25="","",VLOOKUP(E25,'7. Ставки'!$C$3:$E$19,2,0)),"УКАЖИ РОЛЬ") -> УКАЖИ РОЛЬ | Q25: =IFERROR(IF(OR(D25=0,P25=0,D25="",P25=""),"",D25*P25),"ПРОВЕРЬ ЦИФРЫ") -> ПРОВЕРЬ ЦИФРЫ | R25: =IF(Q25="","",Q25+(Q25*$R$2)) -> #VALUE! | S25: без НДС | T25: =IF(OR(D25="",D25=0),"",CONCATENATE(E25," ",C25)) -> DevOps Настройка системы логирования и мониторинга (Prometheus, Grafana) | U25: =IF(OR(D25="",D25=0),"",E25) -> DevOps | V25: =IF(OR(D25="",D25=0),"",D25) -> 4
C26: API Gateway: настройка эндпоинтов, роутинг, rate limiting | D26: 24 | E26: Development Back | F26: 1 | G26: 6 | H26: 2 | J26: Единая точка входа, защищенная от перегрузок (20 req/s) | K26: =IFERROR(IF(OR(F26=0,D26=0,F26="",D26=""),"",ROUNDUP('2. Расчет трудозатрат'!$D26/8*$N$4/'2. Расчет трудозатрат'!$F26,0)),"ПРОВЕРЬ ЦИФРЫ") -> 3 | L26: Нет | P26: =IFERROR(IF(E26="","",VLOOKUP(E26,'7. Ставки'!$C$3:$E$19,2,0)),"УКАЖИ РОЛЬ") -> УКАЖИ РОЛЬ | Q26: =IFERROR(IF(OR(D26=0,P26=0,D26="",P26=""),"",D26*P26),"ПРОВЕРЬ ЦИФРЫ") -> ПРОВЕРЬ ЦИФРЫ | R26: =IF(Q26="","",Q26+(Q26*$R$2)) -> #VALUE! | S26: без НДС | T26: =IF(OR(D26="",D26=0),"",CONCATENATE(E26," ",C26)) -> Development Back API Gateway: настройка эндпоинтов, роутинг, rate limiting | U26: =IF(OR(D26="",D26=0),"",E26) -> Development Back | V26: =IF(OR(D26="",D26=0),"",D26) -> 24
C27: Адаптер GreenAPI: парсинг и нормализация webhooks | D27: 32 | E27: Development Back | F27: 2 | G27: 7 | H27: 2 | I27: Предоставить тестовый аккаунт и токен GreenAPI. Ограничение: только текстовые сообщения. | J27: Сообщения из WhatsApp корректно преобразуются во внутренний формат | K27: =IFERROR(IF(OR(F27=0,D27=0,F27="",D27=""),"",ROUNDUP('2. Расчет трудозатрат'!$D27/8*$N$4/'2. Расчет трудозатрат'!$F27,0)),"ПРОВЕРЬ ЦИФРЫ") -> 2 | L27: Нет | P27: =IFERROR(IF(E27="","",VLOOKUP(E27,'7. Ставки'!$C$3:$E$19,2,0)),"УКАЖИ РОЛЬ") -> УКАЖИ РОЛЬ | Q27: =IFERROR(IF(OR(D27=0,P27=0,D27="",P27=""),"",D27*P27),"ПРОВЕРЬ ЦИФРЫ") -> ПРОВЕРЬ ЦИФРЫ | R27: =IF(Q27="","",Q27+(Q27*$R$2)) -> #VALUE! | S27: без НДС | T27: =IF(OR(D27="",D27=0),"",CONCATENATE(E27," ",C27)) -> Development Back Адаптер GreenAPI: парсинг и нормализация webhooks | U27: =IF(OR(D27="",D27=0),"",E27) -> Development Back | V27: =IF(OR(D27="",D27=0),"",D27) -> 32
C28: Адаптер JivoSite: парсинг и нормализация webhooks | D28: 32 | E28: Development Back | F28: 1 | G28: 12 | H28: 2 | I28: Предоставить тестовый аккаунт JivoSite. | J28: Сообщения из JivoSite корректно преобразуются во внутренний формат | K28: =IFERROR(IF(OR(F28=0,D28=0,F28="",D28=""),"",ROUNDUP('2. Расчет трудозатрат'!$D28/8*$N$4/'2. Расчет трудозатрат'!$F28,0)),"ПРОВЕРЬ ЦИФРЫ") -> 4 | L28: Нет | P28: =IFERROR(IF(E28="","",VLOOKUP(E28,'7. Ставки'!$C$3:$E$19,2,0)),"УКАЖИ РОЛЬ") -> УКАЖИ РОЛЬ | Q28: =IFERROR(IF(OR(D28=0,P28=0,D28="",P28=""),"",D28*P28),"ПРОВЕРЬ ЦИФРЫ") -> ПРОВЕРЬ ЦИФРЫ | R28: =IF(Q28="","",Q28+(Q28*$R$2)) -> #VALUE! | S28: без НДС | T28: =IF(OR(D28="",D28=0),"",CONCATENATE(E28," ",C28)) -> Development Back Адаптер JivoSite: парсинг и нормализация webhooks | U28: =IF(OR(D28="",D28=0),"",E28) -> Development Back | V28: =IF(OR(D28="",D28=0),"",D28) -> 32
C29: Bot Core Orchestrator: чтение из очереди, роутинг запросов | D29: 40 | E29: Development Back | F29: 1 | G29: 13 | H29: 2 | J29: Ядро бота, маршрутизирующее запросы к нужным сервисам | K29: =IFERROR(IF(OR(F29=0,D29=0,F29="",D29=""),"",ROUNDUP('2. Расчет трудозатрат'!$D29/8*$N$4/'2. Расчет трудозатрат'!$F29,0)),"ПРОВЕРЬ ЦИФРЫ") -> 5 | L29: Нет | P29: =IFERROR(IF(E29="","",VLOOKUP(E29,'7. Ставки'!$C$3:$E$19,2,0)),"УКАЖИ РОЛЬ") -> УКАЖИ РОЛЬ | Q29: =IFERROR(IF(OR(D29=0,P29=0,D29="",P29=""),"",D29*P29),"ПРОВЕРЬ ЦИФРЫ") -> ПРОВЕРЬ ЦИФРЫ | R29: =IF(Q29="","",Q29+(Q29*$R$2)) -> #VALUE! | S29: без НДС | T29: =IF(OR(D29="",D29=0),"",CONCATENATE(E29," ",C29)) -> Development Back Bot Core Orchestrator: чтение из очереди, роутинг запросов | U29: =IF(OR(D29="",D29=0),"",E29) -> Development Back | V29: =IF(OR(D29="",D29=0),"",D29) -> 40
C30: Реализация ролевой модели (клиент/менеджер) | D30: 24 | E30: Development Back | F30: 1 | G30: 14 | H30: 2 | I30: Ограничение: только 2 роли, без гранулярных прав. | J30: Логика, применяющая разные права доступа в зависимости от роли | K30: =IFERROR(IF(OR(F30=0,D30=0,F30="",D30=""),"",ROUNDUP('2. Расчет трудозатрат'!$D30/8*$N$4/'2. Расчет трудозатрат'!$F30,0)),"ПРОВЕРЬ ЦИФРЫ") -> 3 | L30: Нет | P30: =IFERROR(IF(E30="","",VLOOKUP(E30,'7. Ставки'!$C$3:$E$19,2,0)),"УКАЖИ РОЛЬ") -> УКАЖИ РОЛЬ | Q30: =IFERROR(IF(OR(D30=0,P30=0,D30="",P30=""),"",D30*P30),"ПРОВЕРЬ ЦИФРЫ") -> ПРОВЕРЬ ЦИФРЫ | R30: =IF(Q30="","",Q30+(Q30*$R$2)) -> #VALUE! | S30: без НДС | T30: =IF(OR(D30="",D30=0),"",CONCATENATE(E30," ",C30)) -> Development Back Реализация ролевой модели (клиент/менеджер) | U30: =IF(OR(D30="",D30=0),"",E30) -> Development Back | V30: =IF(OR(D30="",D30=0),"",D30) -> 24
C31: Реализация глобального кэша запросов (Redis) | D31: 16 | E31: Development Back | F31: 1 | G31: 15 | H31: 2 | I31: Ограничение: TTL кэша = 300 секунд. | J31: Снижение времени ответа на популярные запросы | K31: =IFERROR(IF(OR(F31=0,D31=0,F31="",D31=""),"",ROUNDUP('2. Расчет трудозатрат'!$D31/8*$N$4/'2. Расчет трудозатрат'!$F31,0)),"ПРОВЕРЬ ЦИФРЫ") -> 2 | L31: Нет | P31: =IFERROR(IF(E31="","",VLOOKUP(E31,'7. Ставки'!$C$3:$E$19,2,0)),"УКАЖИ РОЛЬ") -> УКАЖИ РОЛЬ | Q31: =IFERROR(IF(OR(D31=0,P31=0,D31="",P31=""),"",D31*P31),"ПРОВЕРЬ ЦИФРЫ") -> ПРОВЕРЬ ЦИФРЫ | R31: =IF(Q31="","",Q31+(Q31*$R$2)) -> #VALUE! | S31: без НДС | T31: =IF(OR(D31="",D31=0),"",CONCATENATE(E31," ",C31)) -> Development Back Реализация глобального кэша запросов (Redis) | U31: =IF(OR(D31="",D31=0),"",E31) -> Development Back | V31: =IF(OR(D31="",D31=0),"",D31) -> 16
C32: ERP Integration Service: разработка защищенного API | D32: 40 | E32: Development Back | F32: 1 | G32: 16 | H32: 2 | I32: Требование: Заказчик предоставляет стабильный REST API для ERP с документацией. Разработка API для ERP не входит в оценку. | J32: Безопасный сервис для получения данных (заказы, остатки, цены) | K32: =IFERROR(IF(OR(F32=0,D32=0,F32="",D32=""),"",ROUNDUP('2. Расчет трудозатрат'!$D32/8*$N$4/'2. Расчет трудозатрат'!$F32,0)),"ПРОВЕРЬ ЦИФРЫ") -> 5 | L32: Нет | P32: =IFERROR(IF(E32="","",VLOOKUP(E32,'7. Ставки'!$C$3:$E$19,2,0)),"УКАЖИ РОЛЬ") -> УКАЖИ РОЛЬ | Q32: =IFERROR(IF(OR(D32=0,P32=0,D32="",P32=""),"",D32*P32),"ПРОВЕРЬ ЦИФРЫ") -> ПРОВЕРЬ ЦИФРЫ | R32: =IF(Q32="","",Q32+(Q32*$R$2)) -> #VALUE! | S32: без НДС | T32: =IF(OR(D32="",D32=0),"",CONCATENATE(E32," ",C32)) -> Development Back ERP Integration Service: разработка защищенного API | U32: =IF(OR(D32="",D32=0),"",E32) -> Development Back | V32: =IF(OR(D32="",D32=0),"",D32) -> 40
C33: Реализация логики авторизации (проверка прав на заказ) | D33: 32 | E33: Development Back | F33: 1 | G33: 17 | H33: 2 | I33: Ограничение: проверка только по номеру телефона, привязанному к заказу. | J33: Механизм, не позволяющий просматривать чужие заказы | K33: =IFERROR(IF(OR(F33=0,D33=0,F33="",D33=""),"",ROUNDUP('2. Расчет трудозатрат'!$D33/8*$N$4/'2. Расчет трудозатрат'!$F33,0)),"ПРОВЕРЬ ЦИФРЫ") -> 4 | L33: Нет | P33: =IFERROR(IF(E33="","",VLOOKUP(E33,'7. Ставки'!$C$3:$E$19,2,0)),"УКАЖИ РОЛЬ") -> УКАЖИ РОЛЬ | Q33: =IFERROR(IF(OR(D33=0,P33=0,D33="",P33=""),"",D33*P33),"ПРОВЕРЬ ЦИФРЫ") -> ПРОВЕРЬ ЦИФРЫ | R33: =IF(Q33="","",Q33+(Q33*$R$2)) -> #VALUE! | S33: без НДС | T33: =IF(OR(D33="",D33=0),"",CONCATENATE(E33," ",C33)) -> Development Back Реализация логики авторизации (проверка прав на заказ) | U33: =IF(OR(D33="",D33=0),"",E33) -> Development Back | V33: =IF(OR(D33="",D33=0),"",D33) -> 32
C34: Confluence Indexer: выгрузка, парсинг, чанкинг | D34: 32 | E34: DS/Ai/ML | F34: 1 | G34: 13 | H34: 2 | I34: Ограничение: качество ответов зависит от качества данных в Confluence. Работа с данными не входит в оценку. | J34: Фоновый сервис, который наполняет Vector DB | K34: =IFERROR(IF(OR(F34=0,D34=0,F34="",D34=""),"",ROUNDUP('2. Расчет трудозатрат'!$D34/8*$N$4/'2. Расчет трудозатрат'!$F34,0)),"ПРОВЕРЬ ЦИФРЫ") -> 4 | L34: Нет | P34: =IFERROR(IF(E34="","",VLOOKUP(E34,'7. Ставки'!$C$3:$E$19,2,0)),"УКАЖИ РОЛЬ") -> УКАЖИ РОЛЬ | Q34: =IFERROR(IF(OR(D34=0,P34=0,D34="",P34=""),"",D34*P34),"ПРОВЕРЬ ЦИФРЫ") -> ПРОВЕРЬ ЦИФРЫ | R34: =IF(Q34="","",Q34+(Q34*$R$2)) -> #VALUE! | S34: без НДС | T34: =IF(OR(D34="",D34=0),"",CONCATENATE(E34," ",C34)) -> DS/Ai/ML Confluence Indexer: выгрузка, парсинг, чанкинг | U34: =IF(OR(D34="",D34=0),"",E34) -> DS/Ai/ML | V34: =IF(OR(D34="",D34=0),"",D34) -> 32
C35: RAG Service: API, интеграция с Vector DB и LLM | D35: 72 | E35: DS/Ai/ML | F35: 1 | G35: 16 | H35: 2 | J35: Сервис, генерирующий ответы на основе данных из Confluence | K35: =IFERROR(IF(OR(F35=0,D35=0,F35="",D35=""),"",ROUNDUP('2. Расчет трудозатрат'!$D35/8*$N$4/'2. Расчет трудозатрат'!$F35,0)),"ПРОВЕРЬ ЦИФРЫ") -> 9 | L35: Нет | P35: =IFERROR(IF(E35="","",VLOOKUP(E35,'7. Ставки'!$C$3:$E$19,2,0)),"УКАЖИ РОЛЬ") -> УКАЖИ РОЛЬ | Q35: =IFERROR(IF(OR(D35=0,P35=0,D35="",P35=""),"",D35*P35),"ПРОВЕРЬ ЦИФРЫ") -> ПРОВЕРЬ ЦИФРЫ | R35: =IF(Q35="","",Q35+(Q35*$R$2)) -> #VALUE! | S35: без НДС | T35: =IF(OR(D35="",D35=0),"",CONCATENATE(E35," ",C35)) -> DS/Ai/ML RAG Service: API, интеграция с Vector DB и LLM | U35: =IF(OR(D35="",D35=0),"",E35) -> DS/Ai/ML | V35: =IF(OR(D35="",D35=0),"",D35) -> 72
C36: Подключение облачной LLM и подклчюение к Embedding моделям | D36: 40 | E36: DS/Ai/ML | F36: 1 | G36: 17 | H36: 2 | I36: Выделить сервер с GPU. Ограничение: используется предобученная open-source модель, ее дообучение (fine-tuning) не входит в MVP. | J36: Экономичный сервис для генерации и векторизации | K36: =IFERROR(IF(OR(F36=0,D36=0,F36="",D36=""),"",ROUNDUP('2. Расчет трудозатрат'!$D36/8*$N$4/'2. Расчет трудозатрат'!$F36,0)),"ПРОВЕРЬ ЦИФРЫ") -> 5 | L36: Нет | P36: =IFERROR(IF(E36="","",VLOOKUP(E36,'7. Ставки'!$C$3:$E$19,2,0)),"УКАЖИ РОЛЬ") -> УКАЖИ РОЛЬ | Q36: =IFERROR(IF(OR(D36=0,P36=0,D36="",P36=""),"",D36*P36),"ПРОВЕРЬ ЦИФРЫ") -> ПРОВЕРЬ ЦИФРЫ | R36: =IF(Q36="","",Q36+(Q36*$R$2)) -> #VALUE! | S36: без НДС | T36: =IF(OR(D36="",D36=0),"",CONCATENATE(E36," ",C36)) -> DS/Ai/ML Подключение облачной LLM и подклчюение к Embedding моделям | U36: =IF(OR(D36="",D36=0),"",E36) -> DS/Ai/ML | V36: =IF(OR(D36="",D36=0),"",D36) -> 40
C37: Notification Dispatcher: асинхронная отправка ответов | D37: 24 | E37: Development Back | F37: 1 | G37: 21 | H37: 2 | J37: Отказоустойчивый сервис отправки сообщений | K37: =IFERROR(IF(OR(F37=0,D37=0,F37="",D37=""),"",ROUNDUP('2. Расчет трудозатрат'!$D37/8*$N$4/'2. Расчет трудозатрат'!$F37,0)),"ПРОВЕРЬ ЦИФРЫ") -> 3 | L37: Нет | P37: =IFERROR(IF(E37="","",VLOOKUP(E37,'7. Ставки'!$C$3:$E$19,2,0)),"УКАЖИ РОЛЬ") -> УКАЖИ РОЛЬ | Q37: =IFERROR(IF(OR(D37=0,P37=0,D37="",P37=""),"",D37*P37),"ПРОВЕРЬ ЦИФРЫ") -> ПРОВЕРЬ ЦИФРЫ | R37: =IF(Q37="","",Q37+(Q37*$R$2)) -> #VALUE! | S37: без НДС | T37: =IF(OR(D37="",D37=0),"",CONCATENATE(E37," ",C37)) -> Development Back Notification Dispatcher: асинхронная отправка ответов | U37: =IF(OR(D37="",D37=0),"",E37) -> Development Back | V37: =IF(OR(D37="",D37=0),"",D37) -> 24
C38: Интеграция всех сервисов со структурированным логированием | D38: 32 | E38: Development Back | F38: 1 | G38: 22 | H38: 2 | J38: Все события и ошибки в системе логируются для анализа SLA | K38: =IFERROR(IF(OR(F38=0,D38=0,F38="",D38=""),"",ROUNDUP('2. Расчет трудозатрат'!$D38/8*$N$4/'2. Расчет трудозатрат'!$F38,0)),"ПРОВЕРЬ ЦИФРЫ") -> 4 | L38: Нет | P38: =IFERROR(IF(E38="","",VLOOKUP(E38,'7. Ставки'!$C$3:$E$19,2,0)),"УКАЖИ РОЛЬ") -> УКАЖИ РОЛЬ | Q38: =IFERROR(IF(OR(D38=0,P38=0,D38="",P38=""),"",D38*P38),"ПРОВЕРЬ ЦИФРЫ") -> ПРОВЕРЬ ЦИФРЫ | R38: =IF(Q38="","",Q38+(Q38*$R$2)) -> #VALUE! | S38: без НДС | T38: =IF(OR(D38="",D38=0),"",CONCATENATE(E38," ",C38)) -> Development Back Интеграция всех сервисов со структурированным логированием | U38: =IF(OR(D38="",D38=0),"",E38) -> Development Back | V38: =IF(OR(D38="",D38=0),"",D38) -> 32
A39: 4 | B39: Testing (Тестирование) | K39: =IFERROR(IF(OR(F39=0,D39=0,F39="",D39=""),"",ROUNDUP('2. Расчет трудозатрат'!$D39/8*$N$4/'2. Расчет трудозатрат'!$F39,0)),"ПРОВЕРЬ ЦИФРЫ") | P39: =IFERROR(IF(E39="","",VLOOKUP(E39,'7. Ставки'!$C$3:$E$19,2,0)),"УКАЖИ РОЛЬ") | Q39: =IFERROR(IF(OR(D39=0,P39=0,D39="",P39=""),"",D39*P39),"ПРОВЕРЬ ЦИФРЫ") | R39: =IF(Q39="","",Q39+(Q39*$R$2)) | T39: =IF(OR(D39="",D39=0),"",CONCATENATE(E39," ",C39)) | U39: =IF(OR(D39="",D39=0),"",E39) | V39: =IF(OR(D39="",D39=0),"",D39)
C40: Разработка тест-плана и тест-кейсов | D40: 24 | E40: QA | F40: 1 | G40: 15 | H40: 3 | J40: Документация, покрывающая все функциональные требования | K40: =IFERROR(IF(OR(F40=0,D40=0,F40="",D40=""),"",ROUNDUP('2. Расчет трудозатрат'!$D40/8*$N$4/'2. Расчет трудозатрат'!$F40,0)),"ПРОВЕРЬ ЦИФРЫ") -> 3 | L40: Нет | P40: =IFERROR(IF(E40="","",VLOOKUP(E40,'7. Ставки'!$C$3:$E$19,2,0)),"УКАЖИ РОЛЬ") -> УКАЖИ РОЛЬ | Q40: =IFERROR(IF(OR(D40=0,P40=0,D40="",P40=""),"",D40*P40),"ПРОВЕРЬ ЦИФРЫ") -> ПРОВЕРЬ ЦИФРЫ | R40: =IF(Q40="","",Q40+(Q40*$R$2)) -> #VALUE! | S40: без НДС | T40: =IF(OR(D40="",D40=0),"",CONCATENATE(E40," ",C40)) -> QA Разработка тест-плана и тест-кейсов | U40: =IF(OR(D40="",D40=0),"",E40) -> QA | V40: =IF(OR(D40="",D40=0),"",D40) -> 24
C41: Компонентное и интеграционное тестирование API | D41: 32 | E41: QA | F41: 1 | G41: 16 | H41: 3 | J41: Отчеты о дефектах на уровне отдельных сервисов | K41: =IFERROR(IF(OR(F41=0,D41=0,F41="",D41=""),"",ROUNDUP('2. Расчет трудозатрат'!$D41/8*$N$4/'2. Расчет трудозатрат'!$F41,0)),"ПРОВЕРЬ ЦИФРЫ") -> 4 | L41: Нет | P41: =IFERROR(IF(E41="","",VLOOKUP(E41,'7. Ставки'!$C$3:$E$19,2,0)),"УКАЖИ РОЛЬ") -> УКАЖИ РОЛЬ | Q41: =IFERROR(IF(OR(D41=0,P41=0,D41="",P41=""),"",D41*P41),"ПРОВЕРЬ ЦИФРЫ") -> ПРОВЕРЬ ЦИФРЫ | R41: =IF(Q41="","",Q41+(Q41*$R$2)) -> #VALUE! | S41: без НДС | T41: =IF(OR(D41="",D41=0),"",CONCATENATE(E41," ",C41)) -> QA Компонентное и интеграционное тестирование API | U41: =IF(OR(D41="",D41=0),"",E41) -> QA | V41: =IF(OR(D41="",D41=0),"",D41) -> 32
C42: E2E тестирование сквозных сценариев (WhatsApp, Jivo) | D42: 24 | E42: QA | G42: 17 | H42: 3 | I42: Предоставить тестовые данные (заказы, статьи в Confluence) | J42: Проверенные сценарии "вопрос-ответ" | K42: =IFERROR(IF(OR(F42=0,D42=0,F42="",D42=""),"",ROUNDUP('2. Расчет трудозатрат'!$D42/8*$N$4/'2. Расчет трудозатрат'!$F42,0)),"ПРОВЕРЬ ЦИФРЫ") | L42: Нет | P42: =IFERROR(IF(E42="","",VLOOKUP(E42,'7. Ставки'!$C$3:$E$19,2,0)),"УКАЖИ РОЛЬ") -> УКАЖИ РОЛЬ | Q42: =IFERROR(IF(OR(D42=0,P42=0,D42="",P42=""),"",D42*P42),"ПРОВЕРЬ ЦИФРЫ") -> ПРОВЕРЬ ЦИФРЫ | R42: =IF(Q42="","",Q42+(Q42*$R$2)) -> #VALUE! | S42: без НДС | T42: =IF(OR(D42="",D42=0),"",CONCATENATE(E42," ",C42)) -> QA E2E тестирование сквозных сценариев (WhatsApp, Jivo) | U42: =IF(OR(D42="",D42=0),"",E42) -> QA | V42: =IF(OR(D42="",D42=0),"",D42) -> 24
C43: Тестирование безопасности (проверка доступа к чужим заказам) | D43: 24 | E43: QA | F43: 1 | G43: 23 | H43: 3 | J43: Подтверждение, что клиенты не видят данные менеджеров и чужие заказы | K43: =IFERROR(IF(OR(F43=0,D43=0,F43="",D43=""),"",ROUNDUP('2. Расчет трудозатрат'!$D43/8*$N$4/'2. Расчет трудозатрат'!$F43,0)),"ПРОВЕРЬ ЦИФРЫ") -> 3 | L43: Нет | P43: =IFERROR(IF(E43="","",VLOOKUP(E43,'7. Ставки'!$C$3:$E$19,2,0)),"УКАЖИ РОЛЬ") -> УКАЖИ РОЛЬ | Q43: =IFERROR(IF(OR(D43=0,P43=0,D43="",P43=""),"",D43*P43),"ПРОВЕРЬ ЦИФРЫ") -> ПРОВЕРЬ ЦИФРЫ | R43: =IF(Q43="","",Q43+(Q43*$R$2)) -> #VALUE! | S43: без НДС | T43: =IF(OR(D43="",D43=0),"",CONCATENATE(E43," ",C43)) -> QA Тестирование безопасности (проверка доступа к чужим заказам) | U43: =IF(OR(D43="",D43=0),"",E43) -> QA | V43: =IF(OR(D43="",D43=0),"",D43) -> 24
C44: Нагрузочное тестирование | D44: 24 | E44: QA | F44: 1 | G44: 21 | H44: 3 | I44: Ограничение: SLA ≤ 10 сек (p95) измеряется на сервере, без учета задержек сети. | J44: Отчет о производительности системы под нагрузкой | K44: =IFERROR(IF(OR(F44=0,D44=0,F44="",D44=""),"",ROUNDUP('2. Расчет трудозатрат'!$D44/8*$N$4/'2. Расчет трудозатрат'!$F44,0)),"ПРОВЕРЬ ЦИФРЫ") -> 3 | L44: Нет | P44: =IFERROR(IF(E44="","",VLOOKUP(E44,'7. Ставки'!$C$3:$E$19,2,0)),"УКАЖИ РОЛЬ") -> УКАЖИ РОЛЬ | Q44: =IFERROR(IF(OR(D44=0,P44=0,D44="",P44=""),"",D44*P44),"ПРОВЕРЬ ЦИФРЫ") -> ПРОВЕРЬ ЦИФРЫ | R44: =IF(Q44="","",Q44+(Q44*$R$2)) -> #VALUE! | S44: без НДС | T44: =IF(OR(D44="",D44=0),"",CONCATENATE(E44," ",C44)) -> QA Нагрузочное тестирование | U44: =IF(OR(D44="",D44=0),"",E44) -> QA | V44: =IF(OR(D44="",D44=0),"",D44) -> 24
C45: Регрессионное тестирование и стабилизация | D45: 32 | E45: QA | F45: 1 | G45: 22 | H45: 3 | J45: Стабильная версия продукта, готовая к развертыванию | K45: =IFERROR(IF(OR(F45=0,D45=0,F45="",D45=""),"",ROUNDUP('2. Расчет трудозатрат'!$D45/8*$N$4/'2. Расчет трудозатрат'!$F45,0)),"ПРОВЕРЬ ЦИФРЫ") -> 4 | L45: Нет | P45: =IFERROR(IF(E45="","",VLOOKUP(E45,'7. Ставки'!$C$3:$E$19,2,0)),"УКАЖИ РОЛЬ") -> УКАЖИ РОЛЬ | Q45: =IFERROR(IF(OR(D45=0,P45=0,D45="",P45=""),"",D45*P45),"ПРОВЕРЬ ЦИФРЫ") -> ПРОВЕРЬ ЦИФРЫ | R45: =IF(Q45="","",Q45+(Q45*$R$2)) -> #VALUE! | S45: без НДС | T45: =IF(OR(D45="",D45=0),"",CONCATENATE(E45," ",C45)) -> QA Регрессионное тестирование и стабилизация | U45: =IF(OR(D45="",D45=0),"",E45) -> QA | V45: =IF(OR(D45="",D45=0),"",D45) -> 32
A46: 5 | B46: Развертывание | P46: =IFERROR(IF(E46="","",VLOOKUP(E46,'7. Ставки'!$C$3:$E$19,2,0)),"УКАЖИ РОЛЬ") | Q46: =IFERROR(IF(OR(D46=0,P46=0,D46="",P46=""),"",D46*P46),"ПРОВЕРЬ ЦИФРЫ") | R46: =IF(Q46="","",Q46+(Q46*$R$2)) | T46: =IF(OR(D46="",D46=0),"",CONCATENATE(E46," ",C46)) | U46: =IF(OR(D46="",D46=0),"",E46) | V46: =IF(OR(D46="",D46=0),"",D46)
C47: Развертывание в production-окружении | D47: 8 | E47: DevOps | F47: 1 | G47: 23 | H47: 4 | J47: Система развернута и работает в продуктивной среде | K47: =IFERROR(IF(OR(F47=0,D47=0,F47="",D47=""),"",ROUNDUP('2. Расчет трудозатрат'!$D47/8*$N$4/'2. Расчет трудозатрат'!$F47,0)),"ПРОВЕРЬ ЦИФРЫ") -> 1 | L47: Нет | P47: =IFERROR(IF(E47="","",VLOOKUP(E47,'7. Ставки'!$C$3:$E$19,2,0)),"УКАЖИ РОЛЬ") -> УКАЖИ РОЛЬ | Q47: =IFERROR(IF(OR(D47=0,P47=0,D47="",P47=""),"",D47*P47),"ПРОВЕРЬ ЦИФРЫ") -> ПРОВЕРЬ ЦИФРЫ | R47: =IF(Q47="","",Q47+(Q47*$R$2)) -> #VALUE! | S47: без НДС | T47: =IF(OR(D47="",D47=0),"",CONCATENATE(E47," ",C47)) -> DevOps Развертывание в production-окружении | U47: =IF(OR(D47="",D47=0),"",E47) -> DevOps | V47: =IF(OR(D47="",D47=0),"",D47) -> 8
C48: Подготовка технической и пользовательской документации | D48: 32 | E48: Analytics Busines | F48: 1 | G48: 16 | H48: 4 | J48: Комплект документации для администраторов и пользователей | K48: =IFERROR(IF(OR(F48=0,D48=0,F48="",D48=""),"",ROUNDUP('2. Расчет трудозатрат'!$D48/8*$N$4/'2. Расчет трудозатрат'!$F48,0)),"ПРОВЕРЬ ЦИФРЫ") -> 4 | L48: Нет | P48: =IFERROR(IF(E48="","",VLOOKUP(E48,'7. Ставки'!$C$3:$E$19,2,0)),"УКАЖИ РОЛЬ") -> УКАЖИ РОЛЬ | Q48: =IFERROR(IF(OR(D48=0,P48=0,D48="",P48=""),"",D48*P48),"ПРОВЕРЬ ЦИФРЫ") -> ПРОВЕРЬ ЦИФРЫ | R48: =IF(Q48="","",Q48+(Q48*$R$2)) -> #VALUE! | S48: без НДС | T48: =IF(OR(D48="",D48=0),"",CONCATENATE(E48," ",C48)) -> Analytics Busines Подготовка технической и пользовательской документации | U48: =IF(OR(D48="",D48=0),"",E48) -> Analytics Busines | V48: =IF(OR(D48="",D48=0),"",D48) -> 32
C49: Демонстрация и передача проекта Заказчику | D49: 16 | E49: Product | F49: 1 | G49: 32 | H49: 4 | J49: Проект принят Заказчиком | K49: =IFERROR(IF(OR(F49=0,D49=0,F49="",D49=""),"",ROUNDUP('2. Расчет трудозатрат'!$D49/8*$N$4/'2. Расчет трудозатрат'!$F49,0)),"ПРОВЕРЬ ЦИФРЫ") -> 2 | L49: Нет | P49: =IFERROR(IF(E49="","",VLOOKUP(E49,'7. Ставки'!$C$3:$E$19,2,0)),"УКАЖИ РОЛЬ") -> УКАЖИ РОЛЬ | Q49: =IFERROR(IF(OR(D49=0,P49=0,D49="",P49=""),"",D49*P49),"ПРОВЕРЬ ЦИФРЫ") -> ПРОВЕРЬ ЦИФРЫ | R49: =IF(Q49="","",Q49+(Q49*$R$2)) -> #VALUE! | S49: без НДС | T49: =IF(OR(D49="",D49=0),"",CONCATENATE(E49," ",C49)) -> Product Демонстрация и передача проекта Заказчику | U49: =IF(OR(D49="",D49=0),"",E49) -> Product | V49: =IF(OR(D49="",D49=0),"",D49) -> 16
B50: Managment (Управление) | G50: 24 | P50: =IFERROR(IF(E50="","",VLOOKUP(E50,'7. Ставки'!$C$3:$E$19,2,0)),"УКАЖИ РОЛЬ") | Q50: =IFERROR(IF(OR(D50=0,P50=0,D50="",P50=""),"",D50*P50),"ПРОВЕРЬ ЦИФРЫ") | R50: =IF(Q50="","",Q50+(Q50*$R$2)) | T50: =IF(OR(D50="",D50=0),"",CONCATENATE(E50," ",C50)) | U50: =IF(OR(D50="",D50=0),"",E50) | V50: =IF(OR(D50="",D50=0),"",D50)
C51: Коммуникации (детализация, daily, weekly) | D51: 16 | E51: DSLead | F51: 1 | G51: 33 | H51: 5 | K51: =IFERROR(IF(OR(F51=0,D51=0,F51="",D51=""),"",ROUNDUP('2. Расчет трудозатрат'!$D51/8*$N$4/'2. Расчет трудозатрат'!$F51,0)),"ПРОВЕРЬ ЦИФРЫ") -> 2 | L51: Нет | P51: =IFERROR(IF(E51="","",VLOOKUP(E51,'7. Ставки'!$C$3:$E$19,2,0)),"УКАЖИ РОЛЬ") -> УКАЖИ РОЛЬ | Q51: =IFERROR(IF(OR(D51=0,P51=0,D51="",P51=""),"",D51*P51),"ПРОВЕРЬ ЦИФРЫ") -> ПРОВЕРЬ ЦИФРЫ | R51: =IF(Q51="","",Q51+(Q51*$R$2)) -> #VALUE! | S51: без НДС | T51: =IF(OR(D51="",D51=0),"",CONCATENATE(E51," ",C51)) -> DSLead Коммуникации (детализация, daily, weekly) | U51: =IF(OR(D51="",D51=0),"",E51) -> DSLead | V51: =IF(OR(D51="",D51=0),"",D51) -> 16
C52: Коммуникации (детализация, daily, weekly) | D52: 16 | E52: Development | F52: 1 | G52: 33 | H52: 5 | K52: =IFERROR(IF(OR(F52=0,D52=0,F52="",D52=""),"",ROUNDUP('2. Расчет трудозатрат'!$D52/8*$N$4/'2. Расчет трудозатрат'!$F52,0)),"ПРОВЕРЬ ЦИФРЫ") -> 2 | L52: Нет | P52: =IFERROR(IF(E52="","",VLOOKUP(E52,'7. Ставки'!$C$3:$E$19,2,0)),"УКАЖИ РОЛЬ") -> УКАЖИ РОЛЬ | Q52: =IFERROR(IF(OR(D52=0,P52=0,D52="",P52=""),"",D52*P52),"ПРОВЕРЬ ЦИФРЫ") -> ПРОВЕРЬ ЦИФРЫ | R52: =IF(Q52="","",Q52+(Q52*$R$2)) -> #VALUE! | S52: без НДС | T52: =IF(OR(D52="",D52=0),"",CONCATENATE(E52," ",C52)) -> Development Коммуникации (детализация, daily, weekly) | U52: =IF(OR(D52="",D52=0),"",E52) -> Development | V52: =IF(OR(D52="",D52=0),"",D52) -> 16
C53: Коммуникации (детализация, daily, weekly) | D53: 16 | E53: DS/Ai/ML | F53: 1 | G53: 33 | H53: 5 | K53: =IFERROR(IF(OR(F53=0,D53=0,F53="",D53=""),"",ROUNDUP('2. Расчет трудозатрат'!$D53/8*$N$4/'2. Расчет трудозатрат'!$F53,0)),"ПРОВЕРЬ ЦИФРЫ") -> 2 | L53: Нет | P53: =IFERROR(IF(E53="","",VLOOKUP(E53,'7. Ставки'!$C$3:$E$19,2,0)),"УКАЖИ РОЛЬ") -> УКАЖИ РОЛЬ | Q53: =IFERROR(IF(OR(D53=0,P53=0,D53="",P53=""),"",D53*P53),"ПРОВЕРЬ ЦИФРЫ") -> ПРОВЕРЬ ЦИФРЫ | R53: =IF(Q53="","",Q53+(Q53*$R$2)) -> #VALUE! | S53: без НДС | T53: =IF(OR(D53="",D53=0),"",CONCATENATE(E53," ",C53)) -> DS/Ai/ML Коммуникации (детализация, daily, weekly) | U53: =IF(OR(D53="",D53=0),"",E53) -> DS/Ai/ML | V53: =IF(OR(D53="",D53=0),"",D53) -> 16
C54: Коммуникации (детализация, daily, weekly) | D54: 2 | E54: DevOps | F54: 1 | G54: 33 | H54: 5 | K54: =IFERROR(IF(OR(F54=0,D54=0,F54="",D54=""),"",ROUNDUP('2. Расчет трудозатрат'!$D54/8*$N$4/'2. Расчет трудозатрат'!$F54,0)),"ПРОВЕРЬ ЦИФРЫ") -> 1 | L54: Нет | P54: =IFERROR(IF(E54="","",VLOOKUP(E54,'7. Ставки'!$C$3:$E$19,2,0)),"УКАЖИ РОЛЬ") -> УКАЖИ РОЛЬ | Q54: =IFERROR(IF(OR(D54=0,P54=0,D54="",P54=""),"",D54*P54),"ПРОВЕРЬ ЦИФРЫ") -> ПРОВЕРЬ ЦИФРЫ | R54: =IF(Q54="","",Q54+(Q54*$R$2)) -> #VALUE! | S54: без НДС | T54: =IF(OR(D54="",D54=0),"",CONCATENATE(E54," ",C54)) -> DevOps Коммуникации (детализация, daily, weekly) | U54: =IF(OR(D54="",D54=0),"",E54) -> DevOps | V54: =IF(OR(D54="",D54=0),"",D54) -> 2
C55: Коммуникации (детализация, daily, weekly) | D55: 16 | E55: QA | F55: 1 | G55: 33 | H55: 5 | K55: =IFERROR(IF(OR(F55=0,D55=0,F55="",D55=""),"",ROUNDUP('2. Расчет трудозатрат'!$D55/8*$N$4/'2. Расчет трудозатрат'!$F55,0)),"ПРОВЕРЬ ЦИФРЫ") -> 2 | L55: Нет | P55: =IFERROR(IF(E55="","",VLOOKUP(E55,'7. Ставки'!$C$3:$E$19,2,0)),"УКАЖИ РОЛЬ") -> УКАЖИ РОЛЬ | Q55: =IFERROR(IF(OR(D55=0,P55=0,D55="",P55=""),"",D55*P55),"ПРОВЕРЬ ЦИФРЫ") -> ПРОВЕРЬ ЦИФРЫ | R55: =IF(Q55="","",Q55+(Q55*$R$2)) -> #VALUE! | S55: без НДС | T55: =IF(OR(D55="",D55=0),"",CONCATENATE(E55," ",C55)) -> QA Коммуникации (детализация, daily, weekly) | U55: =IF(OR(D55="",D55=0),"",E55) -> QA | V55: =IF(OR(D55="",D55=0),"",D55) -> 16
C56: Коммуникации (детализация, daily, weekly) | D56: 16 | E56: PM | F56: 1 | G56: 33 | H56: 5 | K56: =IFERROR(IF(OR(F56=0,D56=0,F56="",D56=""),"",ROUNDUP('2. Расчет трудозатрат'!$D56/8*$N$4/'2. Расчет трудозатрат'!$F56,0)),"ПРОВЕРЬ ЦИФРЫ") -> 2 | L56: Нет | P56: =IFERROR(IF(E56="","",VLOOKUP(E56,'7. Ставки'!$C$3:$E$19,2,0)),"УКАЖИ РОЛЬ") -> УКАЖИ РОЛЬ | Q56: =IFERROR(IF(OR(D56=0,P56=0,D56="",P56=""),"",D56*P56),"ПРОВЕРЬ ЦИФРЫ") -> ПРОВЕРЬ ЦИФРЫ | R56: =IF(Q56="","",Q56+(Q56*$R$2)) -> #VALUE! | S56: без НДС | T56: =IF(OR(D56="",D56=0),"",CONCATENATE(E56," ",C56)) -> PM Коммуникации (детализация, daily, weekly) | U56: =IF(OR(D56="",D56=0),"",E56) -> PM | V56: =IF(OR(D56="",D56=0),"",D56) -> 16
C57: Коммуникации (детализация, daily, weekly) | D57: 16 | E57: Architect | F57: 1 | G57: 33 | H57: 5 | K57: =IFERROR(IF(OR(F57=0,D57=0,F57="",D57=""),"",ROUNDUP('2. Расчет трудозатрат'!$D57/8*$N$4/'2. Расчет трудозатрат'!$F57,0)),"ПРОВЕРЬ ЦИФРЫ") -> 2 | L57: Нет | P57: =IFERROR(IF(E57="","",VLOOKUP(E57,'7. Ставки'!$C$3:$E$19,2,0)),"УКАЖИ РОЛЬ") -> УКАЖИ РОЛЬ | Q57: =IFERROR(IF(OR(D57=0,P57=0,D57="",P57=""),"",D57*P57),"ПРОВЕРЬ ЦИФРЫ") -> ПРОВЕРЬ ЦИФРЫ | R57: =IF(Q57="","",Q57+(Q57*$R$2)) -> #VALUE! | S57: без НДС | T57: =IF(OR(D57="",D57=0),"",CONCATENATE(E57," ",C57)) -> Architect Коммуникации (детализация, daily, weekly) | U57: =IF(OR(D57="",D57=0),"",E57) -> Architect | V57: =IF(OR(D57="",D57=0),"",D57) -> 16
C58: Запланированные потери на согласование | D58: 16 | E58: Waste | F58: 1 | G58: 33 | H58: 5 | K58: =IFERROR(IF(OR(F58=0,D58=0,F58="",D58=""),"",ROUNDUP('2. Расчет трудозатрат'!$D58/8*$N$4/'2. Расчет трудозатрат'!$F58,0)),"ПРОВЕРЬ ЦИФРЫ") -> 2 | L58: Нет | P58: =IFERROR(IF(E58="","",VLOOKUP(E58,'7. Ставки'!$C$3:$E$19,2,0)),"УКАЖИ РОЛЬ") -> УКАЖИ РОЛЬ | Q58: =IFERROR(IF(OR(D58=0,P58=0,D58="",P58=""),"",D58*P58),"ПРОВЕРЬ ЦИФРЫ") -> ПРОВЕРЬ ЦИФРЫ | R58: =IF(Q58="","",Q58+(Q58*$R$2)) -> #VALUE! | S58: без НДС | T58: =IF(OR(D58="",D58=0),"",CONCATENATE(E58," ",C58)) -> Waste Запланированные потери на согласование | U58: =IF(OR(D58="",D58=0),"",E58) -> Waste | V58: =IF(OR(D58="",D58=0),"",D58) -> 16
A59: 6 | K59: =IFERROR(IF(OR(F59=0,D59=0,F59="",D59=""),"",ROUNDUP('2. Расчет трудозатрат'!$D59/8*$N$4/'2. Расчет трудозатрат'!$F59,0)),"ПРОВЕРЬ ЦИФРЫ") | P59: =IFERROR(IF(E59="","",VLOOKUP(E59,'7. Ставки'!$C$3:$E$19,2,0)),"УКАЖИ РОЛЬ") | Q59: =IFERROR(IF(OR(D59=0,P59=0,D59="",P59=""),"",D59*P59),"ПРОВЕРЬ ЦИФРЫ") | R59: =IF(Q59="","",Q59+(Q59*$R$2)) | T59: =IF(OR(D59="",D59=0),"",CONCATENATE(E59," ",C59)) | U59: =IF(OR(D59="",D59=0),"",E59) | V59: =IF(OR(D59="",D59=0),"",D59)
K60: =IFERROR(IF(OR(F60=0,D60=0,F60="",D60=""),"",ROUNDUP('2. Расчет трудозатрат'!$D60/8*$N$4/'2. Расчет трудозатрат'!$F60,0)),"ПРОВЕРЬ ЦИФРЫ") | P60: =IFERROR(IF(E60="","",VLOOKUP(E60,'7. Ставки'!$C$3:$E$19,2,0)),"УКАЖИ РОЛЬ") | Q60: =IFERROR(IF(OR(D60=0,P60=0,D60="",P60=""),"",D60*P60),"ПРОВЕРЬ ЦИФРЫ") | R60: =IF(Q60="","",Q60+(Q60*$R$2)) | T60: =IF(OR(D60="",D60=0),"",CONCATENATE(E60," ",C60)) | U60: =IF(OR(D60="",D60=0),"",E60) | V60: =IF(OR(D60="",D60=0),"",D60)
C61: РАЗРАБОТКА часы (сумма групп, кроме 0 "управления"): | D61: =SUM(D14:D60) -> 854 | F61: Вего уникальных потоков | G61: =IFERROR(__xludf.DUMMYFUNCTION("COUNTUNIQUE(G14:G60)"),17.0) -> 17 | H61: Всего этапов КП | I61: =IFERROR(__xludf.DUMMYFUNCTION("COUNTUNIQUE(H14:H60)"),5.0) -> 5 | J61: Количество дней с учётом параллельности выполнения работ (стр.8) | K61: ='1. Расчет проекта'!E15 -> #REF! | P61: Итого без рисков | Q61: =SUM(Q14:Q60) -> 0 | R61: =SUM(R14:R60) -> #VALUE! | S61: без НДС | V61: =IF(C61="","",D61) -> 854
C62: ИТОГО часы (вместе с управлением, но без рисков): | D62: =D61+SUM(D4:D12) -> #REF! | E62: =CONCATENATE("Увеличение часов на: ",ROUND(((D62/D61)-1)*100,1),"%") -> #REF!
C63: ИТОГО часы (весь проект с учётом рисков): | D63: =SUM(#REF!)+SUM(D4:D12) -> #REF! | E63: =CONCATENATE("Увеличение часов на: ",ROUND(((D63/D61)-1)*100,1),"%") -> #REF! | P63: Итого полное | Q63: =Q13+Q61+#REF! -> #REF! | R63: =R13+R61+#REF! -> #VALUE! | S63: без НДС
A65: Идентифицированные риски:
A66: № | B66: Group (Группа риска, если требуется) | C66: Описание риска | D66: Увеличение трудозатрат (ч.) | E66: Исполнитель | F66: Решение по риску
A67: 1 | B67: Data & AI | C67: Неструктурированные или противоречивые данные в Confluence. Статьи содержат много сложных таблиц, схем, устаревшей или конфликтующей информации. Это приведет к неточным или бессмысленным ответам бота (риск не достичь SLA по точности ≥ 90%). | D67: 40 | E67: DSLead | F67: Подтвержден
A68: 2 | B68: Infrastructure & Performance | C68: Низкая производительность API ERP-системы Заказчика. Внутренняя система отвечает на запросы дольше 2-3 секунд, что делает невозможным соблюдение общего SLA по скорости ответа бота (≤ 10 секунд). | D68: 24 | E68: DevOps | F68: Исключен
A69: 3 | B69: Management & Communication | C69: Задержки в предоставлении доступов, данных и согласовании со стороны Заказчика (токены к Confluence/ERP, тестовые данные, утверждение требований). Это приводит к простою команды и срыву сроков этапов. | D69: 72 | E69: PM | F69: Исключен
A70: 4 | B70: External Dependencies | C70: Нестабильная работа или изменение API внешних сервисов (GreenAPI, JivoSite). Сервис может стать недоступным, изменить формат webhooks или ввести новые ограничения, что потребует срочной доработки адаптеров. | D70: 48 | E70: TL | F70: Исключен
A71: 5 | B71: Management & Requirements | C71: Расширение требований (scope creep) в процессе работы над MVP. Например, Заказчик просит добавить поддержку аудиосообщений, кнопок в WhatsApp или интеграцию с Telegram "потому что это просто". | D71: 80 | E71: PM | F71: Исключен
A72: 6 | B72: Security & Infrastructure | C72: Сложности с подключением к внутренним системам Заказчика из-за строгих политик безопасности (закрытые порты, VPN, firewall, отсутствие тестового контура), что замедляет разработку и отладку интеграции с ERP. | D72: 56 | E72: DevOps | F72: Исключен
A73: 7 | B73: AI & User Experience | C73: "Галлюцинации" или нерелевантные ответы LLM, даже при наличии правильного контекста из Confluence. Модель может неправильно интерпретировать контекст или добавлять лишнюю информацию, что снизит доверие пользователей. | D73: 40 | E73: DSLead | F73: Подтвержден

Sheet 3. Скоринг
A1: № | B1: Показатель | C1: Критерии | D1: Оценка риска | E1: Балл | F1: Увеличение стоимости проекта | G1: Примечание | H1: Кто заполняет
A2: 1 | B2: ТКП/договор отражает реальный состав работ | C2: 1. Сформирован состав работ. 2. Определены и включены в договор требования, ТЗ, границы проекта. 3. Оценка трудозатрат согласована Разработкой. 4. PRD согласован Заказчиком. | D2: Низкий | E2: =IF(D2="Высокий",20,IF(D2="Средний",15,0)) -> 0 | F2: =IFS(D2="Отсутствует",0%, D2="Низкий",3%, D2="Средний",5%, D2="Высокий",9%, TRUE,"") -> 0.03 | H2: Продакт/Архитектор
A3: 2 | B3: Архитектура решения | C3: 1. Разработана архитектура решения, позволяющее декомпозировать ее далее до дискретных задач и построить роадмап 2. Архитектор провел ревью проектной документации (PRD) на предмет реализуемости проекта. 3. Архитектура согласована Заказчиком. | D3: Низкий | E3: =IF(D3="Высокий",20,IF(D3="Средний",15,0)) -> 0 | F3: 0 | H3: Архитектор
A4: 3 | B4: Уверенность в реализуемости решения | C4: 1. Отсутствует необходимость доработки легаси-решения 2. Отсутствует зависимость от внешних решений (Если есть полноценная документация на внешнее решение, то риск низкий. Если работали с этим решением, то риска нет. Иначе риск средний или высокий в зависимости от сложности интеграции с решением) 3. Отсутствует зависимость от внешних команд 4. Отсутствует негативный опыт взаимодействия с используемыми технологиями на проекте. | D4: Низкий | F4: 0 | H4: Продакт/Архитектор
A5: 4 | B5: Цели и требования к результатам проекта | C5: 1. Определены цели проекта и требования к результатам проекта и они являются прозрачными для Заказчика. 2. Определены ЛПР со стороны Заказчика, осуществляющие приемку результатов работ. 3. Определены и согласованы критерии приемки решения. 4. Отсутствуют дополнительные (неучтенные) требования к результатам работ. 5. Зафиксированы допущения и ограничения к реализации проекта. | D5: Низкий | E5: =IF(D5="Высокий",20,IF(D5="Средний",15,0)) -> 0 | F5: =IFS(D5="Отсутствует",0%, D5="Низкий",3%, D5="Средний",5%, D5="Высокий",9%, TRUE,"") -> 0.03 | H5: Продакт
A6: 5 | B6: Наличие компетенций | C6: 1. Есть успешный опыт аналогичных проектов у команды проекта. 2. Доступность команды имеющей компетенции для реализации проекта. 3. Есть компетенции в технолгиях и/или домене используемых для реализации проекта. | D6: Низкий | E6: =IF(D6="Высокий",20,IF(D6="Средний",15,0)) -> 0 | F6: =IFS(D6="Отсутствует",0%, D6="Низкий",3%, D6="Средний",5%, D6="Высокий",9%, TRUE,"") -> 0.03 | H6: Архитектор
A7: 6 | B7: Лояльность/сложность Заказчика | C7: 1. Заказчик лоялен. 2. Заказчик обладает опытом внедрения AI решений. 3. Отсутствуют барьеры коммуникаций (локация, язык, доступность Заказчика). 4. Проработанный процесс управления изменениями с Заказчиком. 5. Заказчик обладает опытом работы в формате Заказной разработки. | D7: Отсутствует | E7: =IF(D7="Высокий",20,IF(D7="Средний",15,0)) -> 0 | F7: =IFS(D7="Отсутствует",0%, D7="Низкий",3%, D7="Средний",5%, D7="Высокий",9%, TRUE,"") -> 0 | H7: Продакт/BDM
A8: 7 | B8: Платежеспособность Заказчика | C8: 1. Отсутствие переторжки: прожимания по цене, срокам, скопу работ. 2. Гарантии своевременных оплат. | D8: Низкий | F8: =IFS(D8="Отсутствует",0%, D8="Низкий",3%, D8="Средний",5%, D8="Высокий",9%, TRUE,"") -> 0.03 | H8: Продакт/BDM
A9: 8 | B9: Техническая инфраструктура и интеграции | C9: 1. Определена и согласована технологическая стековая архитектура. 2. Проведена валидация используемых технологий на соответствие требованиям проекта и интеграции с системами заказчика. 3. Определены и зафиксированы в проектной документации (PRD) точки интеграции и API. 4. Заказчик отвечает за работу в своей инфраструктуре и готов выдавать доступы по требованию. | D9: Средний | E9: =IF(D9="Высокий",15,IF(D9="Средний",10,0)) -> 10 | F9: 0 | H9: Архитектор
A10: 9 | B10: Прозрачность процессов работы в проекте (актуально для энтерпрайз-проектов) | C10: Процессы определены и согласованы с заказчиком: Процесс разработки Политики выпуска релизов Процесс проведения предварительных совместных испытаний (ПСИ) Процесс проведения опытной промышленной эксплуатации (ОПЭ) Процесс технико-информационной поддержки Процесс гарантийного сопровождения и управления инцидентами Требования к документированию | D10: Отсутствует | F10: =IFS(D10="Отсутствует",0%, D10="Низкий",3%, D10="Средний",5%, D10="Высокий",9%, TRUE,"") -> 0 | H10: Продакт
A11: 10 | B11: Подтверждение команды | C11: 1. Подтверждено наличие команды на предполагаемую дату старта проекта. 2. Сформирован план выбора замены в случае выхода из строя текущей команды разработки. 3. Отсутствуют доп. требования к команде (локация, тайм-зона, язык, допуски и т.д.) | D11: Отсутствует | E11: =IF(D11="Высокий",15,IF(D11="Средний",10,0)) -> 0 | F11: =IFS(D11="Отсутствует",0%, D11="Низкий",3%, D11="Средний",5%, D11="Высокий",9%, TRUE,"") -> 0 | H11: Продакт
A12: 11 | B12: Готовность заказчика к выполнению работ | C12: 1. Определена дата старт работ (+- неделя). 2. Не ожидаются перерывы при выполнении работ. 3. Подтверждена доступность необходимого для выполнения проекта персонала Заказчика | D12: Отсутствует | E12: =IF(D12="Высокий",10,IF(D12="Средний",6,0)) -> 0 | F12: =IFS(D12="Отсутствует",0%, D12="Низкий",3%, D12="Средний",5%, D12="Высокий",9%, TRUE,"") -> 0 | H12: Продакт
A13: 12 | B13: Сроки работ и орг. составляющая | C13: 1. Календарный план реализации проекта учитывает: - задачи со стороны Заказчика и/или Третьих сторон; - детальный план работ; - резервы на риски; - проведения формальных процедур между нами и Заказчиком. 2. Согласована этапность сдачи результатов работ (срок актирования не превышает 3 месяцев) 3. Отсутствие не сдвигаемых сроков (регламентируемых законодательством, обязательствами Заказчика и т.д.) | D13: Низкий | E13: =IF(D13="Высокий",10,IF(D13="Средний",6,0)) -> 0 | F13: =IFS(D13="Отсутствует",0%, D13="Низкий",3%, D13="Средний",5%, D13="Высокий",9%, TRUE,"") -> 0.03 | H13: Продакт
A14: 13 | B14: Бюджет | C14: 1. Бюджет проекта соответствует договорной стоимости и норме маржинальности, а также включает в себя: - затраты на работы (внутренние и внешние ресурсы); - затраты на командировочные расходы; - накладные расходы; - резервы на риски; - стоимость хостинга, мощностей, ПО и тд; 2. Сроки оплаты по актам не превышают 30 дней. 3. Бюджет Заказчика подтвержден. | D14: Отсутствует | E14: =IF(D14="Высокий",10,IF(D14="Средний",6,0)) -> 0 | F14: =IFS(D14="Отсутствует",0%, D14="Низкий",3%, D14="Средний",5%, D14="Высокий",9%, TRUE,"") -> 0 | H14: Продакт
C15: Итого: | D15: =IFS( F15=0%, "Отсутствует", F15<15%, "Низкий", F15<30%, "Средний", F15<60%, "Высокий", F15>=50%, "Катастрофа", TRUE, "" ) -> Средний | E15: =SUM(E2:E14) -> 10 | F15: =SUM(F2:F14) -> 0.15
